flask_talisman/__init__.py
flask_talisman/talisman.py
flask_talisman/talisman_test.py
flask_talisman-0.8.0.dist-info/LICENSE
flask_talisman-0.8.0.dist-info/METADATA
flask_talisman-0.8.0.dist-info/WHEEL
flask_talisman-0.8.0.dist-info/top_level.txt
flask_talisman-0.8.0.dist-info/RECORD
